rhinotype/SNPeek.py
rhinotype/__init__.py
rhinotype/assign_types.py
rhinotype/count_SNPs.py
rhinotype/distance_helpers.py
rhinotype/genetic_distances.py
rhinotype/getprototypeseqs.py
rhinotype/main.py
rhinotype/overall_mean_distance.py
rhinotype/pairwise_distances.py
rhinotype/plot_AA.py
rhinotype/plot_distances.py
rhinotype/plot_frequency.py
rhinotype/plot_tree.py
rhinotype/readfasta.py
rhinotype/data/Vp4_2_assigned_types.csv
rhinotype/data/input_aln.fasta
rhinotype/data/prototypes.csv
rhinotype/data/prototypes.fasta
rhinotype/data/test.fasta
rhinotype/data/test.translated.fasta
rhinotype/data/vp1_align.fasta
rhinotype/data/vp1_assigned_types.csv
rhinotype/data/vp1_prototypes.fasta
rhinotype/data/vp1_test.csv
rhinotype/data/vp1_test.fasta
rhinotype/data/vp1_test_data.fasta
rhinotype/data/vp1_test_translated.fasta
rhinotype-2.0.0.dist-info/licenses/LICENSE
rhinotype-2.0.0.dist-info/METADATA
rhinotype-2.0.0.dist-info/WHEEL
rhinotype-2.0.0.dist-info/entry_points.txt
rhinotype-2.0.0.dist-info/top_level.txt
rhinotype-2.0.0.dist-info/RECORD
