Metadata-Version: 2.4
Name: rhinotype
Version: 2.0.0
Summary: A python tool used to automatically genotype rhinovirus.
Author-email: Ephantus Wambui <ephywambui72@gmail.com>, Daniel Okoro <ugookorodaniel620@gmail.com>, Andrew Acheampong <acheampongandrews1999@gmail.com>, Parcelli Jepchirchir <parcelmaiyo@gmail.com>, Olaitan Awe <laitanawe@gmail.com>
License: MIT
Project-URL: Homepage, https://github.com/omicscodeathon/rhinotype
Keywords: bioinformatics,virology,genotyping,rhinovirus,genotype
Classifier: Programming Language :: Python :: 3
Classifier: License :: OSI Approved :: MIT License
Requires-Python: >=3.8
License-File: LICENSE
Requires-Dist: matplotlib>=3.8
Requires-Dist: numpy>=2.3
Requires-Dist: pandas>=2.3
Requires-Dist: seaborn>=0.13
Requires-Dist: scipy>=1.16
Requires-Dist: biopython>=1.86
Dynamic: license-file
